pipcherry/__init__.py
pipcherry/main.py
pipcherry-0.1.1.dist-info/METADATA
pipcherry-0.1.1.dist-info/WHEEL
pipcherry-0.1.1.dist-info/top_level.txt
pipcherry-0.1.1.dist-info/RECORD
