Metadata-Version: 2.1
Name: pipcherry
Version: 0.1.1
Summary: A simple Python package
Home-page: https://github.com/yourusername/pipcherry
Author: Your Name
Author-email: your_email@example.com
Classifier: Programming Language :: Python :: 3
Classifier: License :: OSI Approved :: MIT License
Classifier: Operating System :: OS Independent
Requires-Python: >=3.6
